{"use_in_serenity":"U+10CD11","creation_history":"Created by Andreas on July 18th, 2021. Reason: unknown.","description":"A combination of yak shaving and bikeshedding. The latter refers to [procrastination or investing time into unimportant issues](https://en.wiktionary.org/wiki/bikeshedding) (as opposed to yakshaving, where time is invested into only _seemingly_ unimportant issues). The emoji can be used when the distinction is not exactly clear.","image":"https://cdn.discordapp.com/emojis/866370560493223977.png","remark":"~~who tf even came up with this~~","name":"Yakshed"}
